turboyaml/__init__.py
turboyaml/cli.py
turboyaml/utils/__init__.py
turboyaml/utils/dbt_utils.py
turboyaml/utils/openai_utils.py
turboyaml/utils/turboyaml_utils.py
turboyaml/utils/version.py
turboyaml-0.0.6.dist-info/LICENSE
turboyaml-0.0.6.dist-info/METADATA
turboyaml-0.0.6.dist-info/WHEEL
turboyaml-0.0.6.dist-info/entry_points.txt
turboyaml-0.0.6.dist-info/top_level.txt
turboyaml-0.0.6.dist-info/RECORD
