Metadata-Version: 2.1
Name: turboyaml
Version: 0.0.6
Summary: An AI-powered CLI tool for converting DBT SQL files to YAML using OpenAI.
Home-page: https://github.com/fredbrowne/turboyaml
Author: Fred Setra
Author-email: fred.setra@gmail.com
Classifier: Programming Language :: Python :: 3
Classifier: License :: OSI Approved :: MIT License
Classifier: Operating System :: OS Independent
Classifier: Topic :: Software Development :: Libraries
Classifier: Topic :: Utilities
License-File: LICENSE
Requires-Dist: openai ==1.13.3
Requires-Dist: pydantic ==2.6.3
